{"srcdb":"202501","count":2,"results":[{"key":"320","code":"AMS 406","title":"PROJECTS","crn":"14400","no":"501","total":"1","schd":"S","camp":"B","stat":"A","ssrFees":"","isCancelled":"","meets":"","mpkey":"1","meetingTimes":"[]","instr":"J. Rankin","start_date":"2024-09-25","end_date":"2024-12-06","srcdb":"202501"},{"key":"321","code":"AMS 406","title":"PROJECTS: PROJ/ NATIVE AMERICAN STUDIES","crn":"18180","no":"502","total":"1","schd":"S","camp":"B","stat":"A","ssrFees":"","isCancelled":"","meets":"","mpkey":"1","meetingTimes":"[]","instr":"J. Rankin","start_date":"2024-09-25","end_date":"2024-12-06","srcdb":"202501"}]}