{"srcdb":"202501","count":4,"results":[{"key":"911","code":"BA 410","title":"BUSINESS INTERNSHIP","crn":"10522","no":"001","total":"3","schd":"J","camp":"C","stat":"A","ssrFees":"","isCancelled":"","meets":"","mpkey":"1","meetingTimes":"[]","instr":"J. Villalobos","start_date":"2024-09-25","end_date":"2024-12-06","srcdb":"202501"},{"key":"914","code":"BA 410","title":"BUSINESS INTERNSHIP","crn":"14020","no":"400","total":"3","schd":"Y","camp":"DB","stat":"A","ssrFees":"","isCancelled":"","meets":"","mpkey":"1","meetingTimes":"[]","instr":"J. Villalobos","start_date":"2024-09-25","end_date":"2024-12-06","srcdb":"202501"},{"key":"913","code":"BA 410","title":"BUSINESS INTERNSHIP","crn":"13144","no":"501","total":"3","schd":"J","camp":"B","stat":"A","ssrFees":"","isCancelled":"","meets":"","mpkey":"1","meetingTimes":"[]","instr":"K. Vierra","start_date":"2024-09-25","end_date":"2024-12-06","srcdb":"202501"},{"key":"912","code":"BA 410","title":"BUSINESS INTERNSHIP: INTERNSHIP/ MECOP","crn":"12713","no":"010","total":"1","schd":"J","camp":"C","stat":"A","ssrFees":"","isCancelled":"","meets":"","mpkey":"1","meetingTimes":"[]","instr":"L. Martin","start_date":"2024-09-25","end_date":"2024-12-06","srcdb":"202501"}]}