{"srcdb":"202501","count":9,"results":[{"key":"1031","code":"BB 410","title":"INTERNSHIP","crn":"17661","no":"001","total":"2","schd":"J","camp":"C","stat":"A","ssrFees":"","isCancelled":"","meets":"","mpkey":"1","meetingTimes":"[]","instr":"Staff","start_date":"2024-09-25","end_date":"2024-12-06","srcdb":"202501"},{"key":"1032","code":"BB 410","title":"INTERNSHIP","crn":"18976","no":"501","total":"2","schd":"J","camp":"B","stat":"A","ssrFees":"","isCancelled":"","meets":"","mpkey":"1","meetingTimes":"[]","instr":"K. Smith","start_date":"2024-09-25","end_date":"2024-12-06","srcdb":"202501"},{"key":"1152","code":"BEE 410","title":"ECOLOGICAL ENGINEERING INTERNSHIP","crn":"14561","no":"001","total":"2","schd":"J","camp":"C","stat":"A","ssrFees":"","isCancelled":"","meets":"","mpkey":"1","meetingTimes":"[]","instr":"Staff","start_date":"2024-09-25","end_date":"2024-12-06","srcdb":"202501"},{"key":"1153","code":"BEE 410","title":"ECOLOGICAL ENGINEERING INTERNSHIP","crn":"14969","no":"002","total":"2","schd":"J","camp":"C","stat":"A","ssrFees":"","isCancelled":"","meets":"","mpkey":"1","meetingTimes":"[]","instr":"Staff","start_date":"2024-09-25","end_date":"2024-12-06","srcdb":"202501"},{"key":"1194","code":"BHS 410","title":"SCIENCE INTERNSHIP","crn":"19292","no":"001","total":"1","schd":"J","camp":"C","stat":"A","ssrFees":"","isCancelled":"","meets":"","mpkey":"1","meetingTimes":"[]","instr":"L. Bruslind","start_date":"2024-09-25","end_date":"2024-12-06","srcdb":"202501"},{"key":"1342","code":"BI 410","title":"INTERNSHIP","crn":"10602","no":"001","total":"3","schd":"J","camp":"C","stat":"A","ssrFees":"","isCancelled":"","meets":"","mpkey":"1","meetingTimes":"[]","instr":"J. Andicoechea","start_date":"2024-09-25","end_date":"2024-12-06","srcdb":"202501"},{"key":"1344","code":"BI 410","title":"INTERNSHIP","crn":"14716","no":"400","total":"3","schd":"Y","camp":"DB","stat":"A","ssrFees":"","isCancelled":"","meets":"","mpkey":"1","meetingTimes":"[]","instr":"J. Andicoechea","start_date":"2024-09-25","end_date":"2024-12-06","srcdb":"202501"},{"key":"1343","code":"BI 410","title":"INTERNSHIP","crn":"14570","no":"501","total":"3","schd":"J","camp":"B","stat":"A","ssrFees":"","isCancelled":"","meets":"","mpkey":"1","meetingTimes":"[]","instr":"Staff","start_date":"2024-09-25","end_date":"2024-12-06","srcdb":"202501"},{"key":"1509","code":"BRR 410","title":"INTERNSHIP","crn":"10848","no":"001","total":"1","schd":"J","camp":"C","stat":"A","ssrFees":"","isCancelled":"","meets":"","mpkey":"1","meetingTimes":"[]","instr":"W. Crannell","start_date":"2024-09-25","end_date":"2024-12-06","srcdb":"202501"}]}