{"srcdb":"202501","count":6,"results":[{"key":"2488","code":"CS 401","title":"RESEARCH","crn":"18568","no":"001","total":"6","schd":"G","camp":"C","stat":"C","ssrFees":"","isCancelled":"1","meets":"","mpkey":"1","meetingTimes":"[]","instr":"Staff","start_date":"2024-09-25","end_date":"2024-12-06","srcdb":"202501"},{"key":"2489","code":"CS 401","title":"RESEARCH","crn":"18600","no":"002","total":"6","schd":"G","camp":"C","stat":"C","ssrFees":"","isCancelled":"1","meets":"","mpkey":"1","meetingTimes":"[]","instr":"Staff","start_date":"2024-09-25","end_date":"2024-12-06","srcdb":"202501"},{"key":"2490","code":"CS 401","title":"RESEARCH","crn":"20502","no":"003","total":"6","schd":"G","camp":"C","stat":"A","ssrFees":"","isCancelled":"","meets":"","mpkey":"1","meetingTimes":"[]","instr":"Z. Ma","start_date":"2024-09-25","end_date":"2024-12-06","srcdb":"202501"},{"key":"2491","code":"CS 401","title":"RESEARCH","crn":"20505","no":"004","total":"6","schd":"G","camp":"C","stat":"A","ssrFees":"","isCancelled":"","meets":"","mpkey":"1","meetingTimes":"[]","instr":"J. Clark","start_date":"2024-09-25","end_date":"2024-12-06","srcdb":"202501"},{"key":"2492","code":"CS 401","title":"RESEARCH","crn":"20547","no":"005","total":"6","schd":"G","camp":"C","stat":"A","ssrFees":"","isCancelled":"","meets":"","mpkey":"1","meetingTimes":"[]","instr":"V. Immler","start_date":"2024-09-25","end_date":"2024-12-06","srcdb":"202501"},{"key":"2487","code":"CS 401","title":"RESEARCH","crn":"14852","no":"502","total":"6","schd":"G","camp":"B","stat":"A","ssrFees":"","isCancelled":"","meets":"","mpkey":"1","meetingTimes":"[]","instr":"P. Donnelly","start_date":"2024-09-25","end_date":"2024-12-06","srcdb":"202501"}]}