{"srcdb":"202501","count":5,"results":[{"key":"3291","code":"ENG 104Z","title":"*INTRODUCTION TO FICTION","crn":"14767","no":"002","total":"5","schd":"HYB","camp":"C","stat":"F","ssrFees":"","isCancelled":"","meets":"M 2-3:50p","mpkey":"2069","meetingTimes":"[{\"meet_day\":\"0\",\"start_time\":\"1400\",\"end_time\":\"1550\"}]","instr":"M. Norris","start_date":"2024-09-25","end_date":"2024-12-06","srcdb":"202501"},{"key":"3292","code":"ENG 104Z","title":"*INTRODUCTION TO FICTION","crn":"16258","no":"003","total":"5","schd":"HYB","camp":"C","stat":"A","ssrFees":"","isCancelled":"","meets":"W 2-3:50p","mpkey":"2066","meetingTimes":"[{\"meet_day\":\"2\",\"start_time\":\"1400\",\"end_time\":\"1550\"}]","instr":"M. Norris","start_date":"2024-09-25","end_date":"2024-12-06","srcdb":"202501"},{"key":"3289","code":"ENG 104Z","title":"*INTRODUCTION TO FICTION","crn":"11824","no":"400","total":"5","schd":"Y","camp":"DI","stat":"F","ssrFees":"","isCancelled":"","meets":"","mpkey":"1","meetingTimes":"[]","instr":"E. Delf","start_date":"2024-09-25","end_date":"2024-12-06","srcdb":"202501"},{"key":"3290","code":"ENG 104Z","title":"*INTRODUCTION TO FICTION","crn":"14743","no":"401","total":"5","schd":"Y","camp":"DI","stat":"A","ssrFees":"","isCancelled":"","meets":"","mpkey":"1","meetingTimes":"[]","instr":"D. Weaver","start_date":"2024-09-25","end_date":"2024-12-06","srcdb":"202501"},{"key":"3293","code":"ENG 104Z","title":"*INTRODUCTION TO FICTION","crn":"20312","no":"402","total":"5","schd":"Y","camp":"DI","stat":"A","ssrFees":"","isCancelled":"","meets":"","mpkey":"1","meetingTimes":"[]","instr":"O. Blomgren","start_date":"2024-09-25","end_date":"2024-12-06","srcdb":"202501"}]}