{"srcdb":"202501","count":4,"results":[{"key":"3935","code":"FOR 436","title":"WILDLAND FIRE SCIENCE AND MANAGEMENT","crn":"13515","no":"001","total":"4","schd":"A","camp":"C","stat":"F","ssrFees":"11","isCancelled":"","meets":"MWF 1-1:50p","mpkey":"2051","meetingTimes":"[{\"meet_day\":\"0\",\"start_time\":\"1300\",\"end_time\":\"1350\"},{\"meet_day\":\"2\",\"start_time\":\"1300\",\"end_time\":\"1350\"},{\"meet_day\":\"4\",\"start_time\":\"1300\",\"end_time\":\"1350\"}]","instr":"D. Skelly","start_date":"2024-09-25","end_date":"2024-12-06","srcdb":"202501"},{"key":"3936","code":"FOR 436","title":"WILDLAND FIRE SCIENCE AND MANAGEMENT","crn":"13517","no":"010","total":"4","schd":"D","camp":"C","stat":"A","ssrFees":"","isCancelled":"","meets":"F 9-11:50a","mpkey":"2504","meetingTimes":"[{\"meet_day\":\"4\",\"start_time\":\"900\",\"end_time\":\"1150\"}]","instr":"D. Skelly","start_date":"2024-09-25","end_date":"2024-12-06","srcdb":"202501"},{"key":"3938","code":"FOR 436","title":"WILDLAND FIRE SCIENCE AND MANAGEMENT","crn":"19478","no":"011","total":"4","schd":"D","camp":"C","stat":"A","ssrFees":"","isCancelled":"","meets":"F 2-4:50p","mpkey":"2459","meetingTimes":"[{\"meet_day\":\"4\",\"start_time\":\"1400\",\"end_time\":\"1650\"}]","instr":"D. Skelly","start_date":"2024-09-25","end_date":"2024-12-06","srcdb":"202501"},{"key":"3937","code":"FOR 436","title":"WILDLAND FIRE SCIENCE AND MANAGEMENT","crn":"15580","no":"400","total":"4","schd":"Y","camp":"DB","stat":"F","ssrFees":"","isCancelled":"","meets":"","mpkey":"1","meetingTimes":"[]","instr":"B. Horton","start_date":"2024-09-25","end_date":"2024-12-06","srcdb":"202501"}]}