{"srcdb":"202501","count":2,"results":[{"key":"4354","code":"GD 328","title":"INTERACTIVE 2","crn":"12532","no":"001","total":"2","schd":"HYB","camp":"C","stat":"F","ssrFees":"25","isCancelled":"","meets":"MW 8-9:50a","mpkey":"2383","meetingTimes":"[{\"meet_day\":\"0\",\"start_time\":\"800\",\"end_time\":\"950\"},{\"meet_day\":\"2\",\"start_time\":\"800\",\"end_time\":\"950\"}]","instr":"J. Shin","start_date":"2024-09-25","end_date":"2024-12-06","srcdb":"202501"},{"key":"4355","code":"GD 328","title":"INTERACTIVE 2","crn":"13373","no":"002","total":"2","schd":"HYB","camp":"C","stat":"F","ssrFees":"25","isCancelled":"","meets":"MW 12-1:50p","mpkey":"2094","meetingTimes":"[{\"meet_day\":\"0\",\"start_time\":\"1200\",\"end_time\":\"1350\"},{\"meet_day\":\"2\",\"start_time\":\"1200\",\"end_time\":\"1350\"}]","instr":"J. Shin","start_date":"2024-09-25","end_date":"2024-12-06","srcdb":"202501"}]}