{"srcdb":"202501","count":2,"results":[{"key":"4600","code":"GRAD 610","title":"INTERNSHIP","crn":"13468","no":"001","total":"2","schd":"J","camp":"C","stat":"A","ssrFees":"","isCancelled":"","meets":"T 3-5:50p","mpkey":"2029","meetingTimes":"[{\"meet_day\":\"1\",\"start_time\":\"1500\",\"end_time\":\"1750\"}]","instr":"L. Tucker Serniak","start_date":"2024-09-25","end_date":"2024-12-06","srcdb":"202501"},{"key":"4599","code":"GRAD 610","title":"INTERNSHIP","crn":"13172","no":"400","total":"2","schd":"Y","camp":"DB","stat":"A","ssrFees":"","isCancelled":"","meets":"","mpkey":"1","meetingTimes":"[]","instr":"L. Tucker Serniak","start_date":"2024-09-25","end_date":"2024-12-06","srcdb":"202501"}]}