{"srcdb":"202501","count":3,"results":[{"key":"4880","code":"HDFS 447","title":"*FAMILIES AND POVERTY","crn":"14368","no":"001","total":"3","schd":"A","camp":"C","stat":"F","ssrFees":"","isCancelled":"","meets":"TR 2-3:50p","mpkey":"2100","meetingTimes":"[{\"meet_day\":\"1\",\"start_time\":\"1400\",\"end_time\":\"1550\"},{\"meet_day\":\"3\",\"start_time\":\"1400\",\"end_time\":\"1550\"}]","instr":"L. McGraw","start_date":"2024-09-25","end_date":"2024-12-06","srcdb":"202501"},{"key":"4879","code":"HDFS 447","title":"*FAMILIES AND POVERTY","crn":"11897","no":"400","total":"3","schd":"Y","camp":"DB","stat":"A","ssrFees":"","isCancelled":"","meets":"","mpkey":"1","meetingTimes":"[]","instr":"I. de Pierola","start_date":"2024-09-25","end_date":"2024-12-06","srcdb":"202501"},{"key":"4878","code":"HDFS 447","title":"*FAMILIES AND POVERTY","crn":"11867","no":"501","total":"3","schd":"A","camp":"B","stat":"A","ssrFees":"","isCancelled":"","meets":"MW 10-11:20a","mpkey":"2020","meetingTimes":"[{\"meet_day\":\"0\",\"start_time\":\"1000\",\"end_time\":\"1120\"},{\"meet_day\":\"2\",\"start_time\":\"1000\",\"end_time\":\"1120\"}]","instr":"D. Lynn","start_date":"2024-09-25","end_date":"2024-12-06","srcdb":"202501"}]}