{"srcdb":"202501","count":20,"results":[{"key":"5235","code":"IB 603","title":"THESIS","crn":"13007","no":"001","total":"20","schd":"Q","camp":"C","stat":"A","ssrFees":"","isCancelled":"","meets":"","mpkey":"1","meetingTimes":"[]","instr":"F. Barreto","start_date":"2024-09-25","end_date":"2024-12-06","srcdb":"202501"},{"key":"5220","code":"IB 603","title":"THESIS","crn":"10757","no":"002","total":"20","schd":"Q","camp":"C","stat":"A","ssrFees":"","isCancelled":"","meets":"","mpkey":"1","meetingTimes":"[]","instr":"M. Burke","start_date":"2024-09-25","end_date":"2024-12-06","srcdb":"202501"},{"key":"5223","code":"IB 603","title":"THESIS","crn":"10760","no":"003","total":"20","schd":"Q","camp":"C","stat":"A","ssrFees":"","isCancelled":"","meets":"","mpkey":"1","meetingTimes":"[]","instr":"F. Chan","start_date":"2024-09-25","end_date":"2024-12-06","srcdb":"202501"},{"key":"5236","code":"IB 603","title":"THESIS","crn":"13008","no":"004","total":"20","schd":"Q","camp":"C","stat":"A","ssrFees":"","isCancelled":"","meets":"","mpkey":"1","meetingTimes":"[]","instr":"J. Cornelius","start_date":"2024-09-25","end_date":"2024-12-06","srcdb":"202501"},{"key":"5238","code":"IB 603","title":"THESIS","crn":"13010","no":"005","total":"20","schd":"Q","camp":"C","stat":"A","ssrFees":"","isCancelled":"","meets":"","mpkey":"1","meetingTimes":"[]","instr":"B. Dalziel","start_date":"2024-09-25","end_date":"2024-12-06","srcdb":"202501"},{"key":"5237","code":"IB 603","title":"THESIS","crn":"13009","no":"006","total":"20","schd":"Q","camp":"C","stat":"A","ssrFees":"","isCancelled":"","meets":"","mpkey":"1","meetingTimes":"[]","instr":"P. De Leenheer","start_date":"2024-09-25","end_date":"2024-12-06","srcdb":"202501"},{"key":"5230","code":"IB 603","title":"THESIS","crn":"12105","no":"007","total":"20","schd":"Q","camp":"C","stat":"A","ssrFees":"","isCancelled":"","meets":"","mpkey":"1","meetingTimes":"[]","instr":"D. Denver","start_date":"2024-09-25","end_date":"2024-12-06","srcdb":"202501"},{"key":"5228","code":"IB 603","title":"THESIS","crn":"11847","no":"008","total":"20","schd":"Q","camp":"C","stat":"A","ssrFees":"","isCancelled":"","meets":"","mpkey":"1","meetingTimes":"[]","instr":"K. Everson","start_date":"2024-09-25","end_date":"2024-12-06","srcdb":"202501"},{"key":"5226","code":"IB 603","title":"THESIS","crn":"11327","no":"009","total":"20","schd":"Q","camp":"C","stat":"A","ssrFees":"","isCancelled":"","meets":"","mpkey":"1","meetingTimes":"[]","instr":"S. Hacker","start_date":"2024-09-25","end_date":"2024-12-06","srcdb":"202501"},{"key":"5229","code":"IB 603","title":"THESIS","crn":"11938","no":"010","total":"20","schd":"Q","camp":"C","stat":"A","ssrFees":"","isCancelled":"","meets":"","mpkey":"1","meetingTimes":"[]","instr":"S. Henkel","start_date":"2024-09-25","end_date":"2024-12-06","srcdb":"202501"},{"key":"5234","code":"IB 603","title":"THESIS","crn":"12657","no":"011","total":"20","schd":"Q","camp":"C","stat":"A","ssrFees":"","isCancelled":"","meets":"","mpkey":"1","meetingTimes":"[]","instr":"A. Jolles","start_date":"2024-09-25","end_date":"2024-12-06","srcdb":"202501"},{"key":"5225","code":"IB 603","title":"THESIS","crn":"11307","no":"012","total":"20","schd":"Q","camp":"C","stat":"A","ssrFees":"","isCancelled":"","meets":"","mpkey":"1","meetingTimes":"[]","instr":"D. Kikuchi","start_date":"2024-09-25","end_date":"2024-12-06","srcdb":"202501"},{"key":"5227","code":"IB 603","title":"THESIS","crn":"11831","no":"013","total":"20","schd":"Q","camp":"C","stat":"A","ssrFees":"","isCancelled":"","meets":"","mpkey":"1","meetingTimes":"[]","instr":"D. Lytle","start_date":"2024-09-25","end_date":"2024-12-06","srcdb":"202501"},{"key":"5222","code":"IB 603","title":"THESIS","crn":"10759","no":"014","total":"20","schd":"Q","camp":"C","stat":"A","ssrFees":"","isCancelled":"","meets":"","mpkey":"1","meetingTimes":"[]","instr":"B. Menge","start_date":"2024-09-25","end_date":"2024-12-06","srcdb":"202501"},{"key":"5221","code":"IB 603","title":"THESIS","crn":"10758","no":"015","total":"20","schd":"Q","camp":"C","stat":"A","ssrFees":"","isCancelled":"","meets":"","mpkey":"1","meetingTimes":"[]","instr":"M. Novak","start_date":"2024-09-25","end_date":"2024-12-06","srcdb":"202501"},{"key":"5231","code":"IB 603","title":"THESIS","crn":"12347","no":"016","total":"20","schd":"Q","camp":"C","stat":"A","ssrFees":"","isCancelled":"","meets":"","mpkey":"1","meetingTimes":"[]","instr":"M. Orr","start_date":"2024-09-25","end_date":"2024-12-06","srcdb":"202501"},{"key":"5233","code":"IB 603","title":"THESIS","crn":"12609","no":"017","total":"20","schd":"Q","camp":"C","stat":"A","ssrFees":"","isCancelled":"","meets":"","mpkey":"1","meetingTimes":"[]","instr":"M. Phillips","start_date":"2024-09-25","end_date":"2024-12-06","srcdb":"202501"},{"key":"5239","code":"IB 603","title":"THESIS","crn":"17335","no":"018","total":"20","schd":"Q","camp":"C","stat":"A","ssrFees":"","isCancelled":"","meets":"","mpkey":"1","meetingTimes":"[]","instr":"S. Sponaugle","start_date":"2024-09-25","end_date":"2024-12-06","srcdb":"202501"},{"key":"5232","code":"IB 603","title":"THESIS","crn":"12348","no":"019","total":"20","schd":"Q","camp":"C","stat":"A","ssrFees":"","isCancelled":"","meets":"","mpkey":"1","meetingTimes":"[]","instr":"R. Terry Novak","start_date":"2024-09-25","end_date":"2024-12-06","srcdb":"202501"},{"key":"5224","code":"IB 603","title":"THESIS","crn":"10761","no":"020","total":"20","schd":"Q","camp":"C","stat":"A","ssrFees":"","isCancelled":"","meets":"","mpkey":"1","meetingTimes":"[]","instr":"V. Weis","start_date":"2024-09-25","end_date":"2024-12-06","srcdb":"202501"}]}