{"srcdb":"202501","count":4,"results":[{"key":"5929","code":"MTH 228","title":"CALCULUS AND PROBABILITY FOR THE LIFE SCIENCES II","crn":"13527","no":"010","total":"4","schd":"A","camp":"C","stat":"A","ssrFees":"","isCancelled":"","meets":"MWF 3-3:50p","mpkey":"2141","meetingTimes":"[{\"meet_day\":\"0\",\"start_time\":\"1500\",\"end_time\":\"1550\"},{\"meet_day\":\"2\",\"start_time\":\"1500\",\"end_time\":\"1550\"},{\"meet_day\":\"4\",\"start_time\":\"1500\",\"end_time\":\"1550\"}]","instr":"J. Barrett","start_date":"2024-09-25","end_date":"2024-12-06","srcdb":"202501"},{"key":"5930","code":"MTH 228","title":"CALCULUS AND PROBABILITY FOR THE LIFE SCIENCES II","crn":"13528","no":"011","total":"4","schd":"C1","camp":"C","stat":"A","ssrFees":"","isCancelled":"","meets":"R 4-5:20p","mpkey":"2577","meetingTimes":"[{\"meet_day\":\"3\",\"start_time\":\"1600\",\"end_time\":\"1720\"}]","instr":"C. Progin","start_date":"2024-09-25","end_date":"2024-12-06","srcdb":"202501"},{"key":"5931","code":"MTH 228","title":"CALCULUS AND PROBABILITY FOR THE LIFE SCIENCES II","crn":"13529","no":"012","total":"4","schd":"C1","camp":"C","stat":"A","ssrFees":"","isCancelled":"","meets":"R 2-3:20p","mpkey":"2253","meetingTimes":"[{\"meet_day\":\"3\",\"start_time\":\"1400\",\"end_time\":\"1520\"}]","instr":"C. Progin","start_date":"2024-09-25","end_date":"2024-12-06","srcdb":"202501"},{"key":"5932","code":"MTH 228","title":"CALCULUS AND PROBABILITY FOR THE LIFE SCIENCES II","crn":"17288","no":"400","total":"4","schd":"Y","camp":"DI","stat":"A","ssrFees":"","isCancelled":"","meets":"","mpkey":"1","meetingTimes":"[]","instr":"D. Wentland","start_date":"2024-09-25","end_date":"2024-12-06","srcdb":"202501"}]}