{"srcdb":"202501","count":24,"results":[{"key":"6017","code":"MTH 254","title":"VECTOR CALCULUS I","crn":"10138","no":"010","total":"22","schd":"A","camp":"C","stat":"F","ssrFees":"10","isCancelled":"","meets":"MWF 4-4:50p","mpkey":"2178","meetingTimes":"[{\"meet_day\":\"0\",\"start_time\":\"1600\",\"end_time\":\"1650\"},{\"meet_day\":\"2\",\"start_time\":\"1600\",\"end_time\":\"1650\"},{\"meet_day\":\"4\",\"start_time\":\"1600\",\"end_time\":\"1650\"}]","instr":"T. Hatase","start_date":"2024-09-25","end_date":"2024-12-06","srcdb":"202501"},{"key":"6018","code":"MTH 254","title":"VECTOR CALCULUS I","crn":"10139","no":"011","total":"22","schd":"C1","camp":"C","stat":"F","ssrFees":"","isCancelled":"","meets":"R 2-3:20p","mpkey":"2253","meetingTimes":"[{\"meet_day\":\"3\",\"start_time\":\"1400\",\"end_time\":\"1520\"}]","instr":"A. Day","start_date":"2024-09-25","end_date":"2024-12-06","srcdb":"202501"},{"key":"6020","code":"MTH 254","title":"VECTOR CALCULUS I","crn":"11168","no":"012","total":"22","schd":"C1","camp":"C","stat":"F","ssrFees":"","isCancelled":"","meets":"R 4-5:20p","mpkey":"2577","meetingTimes":"[{\"meet_day\":\"3\",\"start_time\":\"1600\",\"end_time\":\"1720\"}]","instr":"A. Day","start_date":"2024-09-25","end_date":"2024-12-06","srcdb":"202501"},{"key":"6022","code":"MTH 254","title":"VECTOR CALCULUS I","crn":"11707","no":"013","total":"22","schd":"C1","camp":"C","stat":"F","ssrFees":"","isCancelled":"","meets":"R 5:30-6:50p","mpkey":"3443","meetingTimes":"[{\"meet_day\":\"3\",\"start_time\":\"1730\",\"end_time\":\"1850\"}]","instr":"A. Day","start_date":"2024-09-25","end_date":"2024-12-06","srcdb":"202501"},{"key":"6019","code":"MTH 254","title":"VECTOR CALCULUS I","crn":"10182","no":"020","total":"22","schd":"A","camp":"C","stat":"F","ssrFees":"10","isCancelled":"","meets":"MWF 3-3:50p","mpkey":"2141","meetingTimes":"[{\"meet_day\":\"0\",\"start_time\":\"1500\",\"end_time\":\"1550\"},{\"meet_day\":\"2\",\"start_time\":\"1500\",\"end_time\":\"1550\"},{\"meet_day\":\"4\",\"start_time\":\"1500\",\"end_time\":\"1550\"}]","instr":"F. Maisch","start_date":"2024-09-25","end_date":"2024-12-06","srcdb":"202501"},{"key":"6021","code":"MTH 254","title":"VECTOR CALCULUS I","crn":"11169","no":"021","total":"22","schd":"C1","camp":"C","stat":"F","ssrFees":"","isCancelled":"","meets":"R 4-5:20p","mpkey":"2577","meetingTimes":"[{\"meet_day\":\"3\",\"start_time\":\"1600\",\"end_time\":\"1720\"}]","instr":"F. Angulo Barba","start_date":"2024-09-25","end_date":"2024-12-06","srcdb":"202501"},{"key":"6023","code":"MTH 254","title":"VECTOR CALCULUS I","crn":"11711","no":"022","total":"22","schd":"C1","camp":"C","stat":"F","ssrFees":"","isCancelled":"","meets":"R 2-3:20p","mpkey":"2253","meetingTimes":"[{\"meet_day\":\"3\",\"start_time\":\"1400\",\"end_time\":\"1520\"}]","instr":"F. Angulo Barba","start_date":"2024-09-25","end_date":"2024-12-06","srcdb":"202501"},{"key":"6028","code":"MTH 254","title":"VECTOR CALCULUS I","crn":"11784","no":"023","total":"22","schd":"C1","camp":"C","stat":"F","ssrFees":"","isCancelled":"","meets":"R 12-1:20p","mpkey":"2134","meetingTimes":"[{\"meet_day\":\"3\",\"start_time\":\"1200\",\"end_time\":\"1320\"}]","instr":"F. Angulo Barba","start_date":"2024-09-25","end_date":"2024-12-06","srcdb":"202501"},{"key":"6029","code":"MTH 254","title":"VECTOR CALCULUS I","crn":"11875","no":"030","total":"22","schd":"A","camp":"C","stat":"A","ssrFees":"10","isCancelled":"","meets":"MWF 9-9:50a","mpkey":"2103","meetingTimes":"[{\"meet_day\":\"0\",\"start_time\":\"900\",\"end_time\":\"950\"},{\"meet_day\":\"2\",\"start_time\":\"900\",\"end_time\":\"950\"},{\"meet_day\":\"4\",\"start_time\":\"900\",\"end_time\":\"950\"}]","instr":"C. Orum","start_date":"2024-09-25","end_date":"2024-12-06","srcdb":"202501"},{"key":"6030","code":"MTH 254","title":"VECTOR CALCULUS I","crn":"11876","no":"031","total":"22","schd":"C1","camp":"C","stat":"F","ssrFees":"","isCancelled":"","meets":"R 8:30-9:50a","mpkey":"2132","meetingTimes":"[{\"meet_day\":\"3\",\"start_time\":\"830\",\"end_time\":\"950\"}]","instr":"N. Elsaesser","start_date":"2024-09-25","end_date":"2024-12-06","srcdb":"202501"},{"key":"6031","code":"MTH 254","title":"VECTOR CALCULUS I","crn":"11877","no":"032","total":"22","schd":"C1","camp":"C","stat":"F","ssrFees":"","isCancelled":"","meets":"R 10-11:20a","mpkey":"2133","meetingTimes":"[{\"meet_day\":\"3\",\"start_time\":\"1000\",\"end_time\":\"1120\"}]","instr":"N. Elsaesser","start_date":"2024-09-25","end_date":"2024-12-06","srcdb":"202501"},{"key":"6032","code":"MTH 254","title":"VECTOR CALCULUS I","crn":"11878","no":"033","total":"22","schd":"C1","camp":"C","stat":"A","ssrFees":"","isCancelled":"","meets":"R 12-1:20p","mpkey":"2134","meetingTimes":"[{\"meet_day\":\"3\",\"start_time\":\"1200\",\"end_time\":\"1320\"}]","instr":"N. Elsaesser","start_date":"2024-09-25","end_date":"2024-12-06","srcdb":"202501"},{"key":"6024","code":"MTH 254","title":"VECTOR CALCULUS I","crn":"11763","no":"040","total":"22","schd":"A","camp":"C","stat":"A","ssrFees":"10","isCancelled":"","meets":"MWF 10-10:50a","mpkey":"2056","meetingTimes":"[{\"meet_day\":\"0\",\"start_time\":\"1000\",\"end_time\":\"1050\"},{\"meet_day\":\"2\",\"start_time\":\"1000\",\"end_time\":\"1050\"},{\"meet_day\":\"4\",\"start_time\":\"1000\",\"end_time\":\"1050\"}]","instr":"F. Maisch","start_date":"2024-09-25","end_date":"2024-12-06","srcdb":"202501"},{"key":"6025","code":"MTH 254","title":"VECTOR CALCULUS I","crn":"11764","no":"041","total":"22","schd":"C1","camp":"C","stat":"A","ssrFees":"","isCancelled":"","meets":"R 8:30-9:50a","mpkey":"2132","meetingTimes":"[{\"meet_day\":\"3\",\"start_time\":\"830\",\"end_time\":\"950\"}]","instr":"M. Phelps","start_date":"2024-09-25","end_date":"2024-12-06","srcdb":"202501"},{"key":"6026","code":"MTH 254","title":"VECTOR CALCULUS I","crn":"11765","no":"042","total":"22","schd":"C1","camp":"C","stat":"F","ssrFees":"","isCancelled":"","meets":"R 10-11:20a","mpkey":"2133","meetingTimes":"[{\"meet_day\":\"3\",\"start_time\":\"1000\",\"end_time\":\"1120\"}]","instr":"M. Phelps","start_date":"2024-09-25","end_date":"2024-12-06","srcdb":"202501"},{"key":"6027","code":"MTH 254","title":"VECTOR CALCULUS I","crn":"11783","no":"043","total":"22","schd":"C1","camp":"C","stat":"F","ssrFees":"","isCancelled":"","meets":"R 12-1:20p","mpkey":"2134","meetingTimes":"[{\"meet_day\":\"3\",\"start_time\":\"1200\",\"end_time\":\"1320\"}]","instr":"M. Phelps","start_date":"2024-09-25","end_date":"2024-12-06","srcdb":"202501"},{"key":"6035","code":"MTH 254","title":"VECTOR CALCULUS I","crn":"17614","no":"050","total":"22","schd":"A","camp":"C","stat":"F","ssrFees":"10","isCancelled":"","meets":"MWF 2-2:50p","mpkey":"2060","meetingTimes":"[{\"meet_day\":\"0\",\"start_time\":\"1400\",\"end_time\":\"1450\"},{\"meet_day\":\"2\",\"start_time\":\"1400\",\"end_time\":\"1450\"},{\"meet_day\":\"4\",\"start_time\":\"1400\",\"end_time\":\"1450\"}]","instr":"C. Orum","start_date":"2024-09-25","end_date":"2024-12-06","srcdb":"202501"},{"key":"6036","code":"MTH 254","title":"VECTOR CALCULUS I","crn":"17615","no":"051","total":"22","schd":"C1","camp":"C","stat":"F","ssrFees":"","isCancelled":"","meets":"R 12-1:20p","mpkey":"2134","meetingTimes":"[{\"meet_day\":\"3\",\"start_time\":\"1200\",\"end_time\":\"1320\"}]","instr":"A. Mills","start_date":"2024-09-25","end_date":"2024-12-06","srcdb":"202501"},{"key":"6037","code":"MTH 254","title":"VECTOR CALCULUS I","crn":"17616","no":"052","total":"22","schd":"C1","camp":"C","stat":"F","ssrFees":"","isCancelled":"","meets":"R 2-3:20p","mpkey":"2253","meetingTimes":"[{\"meet_day\":\"3\",\"start_time\":\"1400\",\"end_time\":\"1520\"}]","instr":"A. Mills","start_date":"2024-09-25","end_date":"2024-12-06","srcdb":"202501"},{"key":"6038","code":"MTH 254","title":"VECTOR CALCULUS I","crn":"17617","no":"053","total":"22","schd":"C1","camp":"C","stat":"F","ssrFees":"","isCancelled":"","meets":"R 4-5:20p","mpkey":"2577","meetingTimes":"[{\"meet_day\":\"3\",\"start_time\":\"1600\",\"end_time\":\"1720\"}]","instr":"A. Mills","start_date":"2024-09-25","end_date":"2024-12-06","srcdb":"202501"},{"key":"6033","code":"MTH 254","title":"VECTOR CALCULUS I","crn":"14373","no":"400","total":"22","schd":"Y","camp":"DI","stat":"A","ssrFees":"","isCancelled":"","meets":"","mpkey":"1","meetingTimes":"[]","instr":"F. Bouya","start_date":"2024-09-25","end_date":"2024-12-06","srcdb":"202501"},{"key":"6034","code":"MTH 254","title":"VECTOR CALCULUS I","crn":"14617","no":"501","total":"22","schd":"A","camp":"B","stat":"A","ssrFees":"","isCancelled":"","meets":"TR 4-5:50p","mpkey":"2346","meetingTimes":"[{\"meet_day\":\"1\",\"start_time\":\"1600\",\"end_time\":\"1750\"},{\"meet_day\":\"3\",\"start_time\":\"1600\",\"end_time\":\"1750\"}]","instr":"C. Ray","start_date":"2024-09-25","end_date":"2024-12-06","srcdb":"202501"},{"key":"6039","code":"MTH 254H","title":"VECTOR CALCULUS I","crn":"11095","no":"001","total":"2","schd":"A","camp":"C","stat":"F","ssrFees":"10","isCancelled":"","meets":"MW 2-3:50p","mpkey":"2090","meetingTimes":"[{\"meet_day\":\"0\",\"start_time\":\"1400\",\"end_time\":\"1550\"},{\"meet_day\":\"2\",\"start_time\":\"1400\",\"end_time\":\"1550\"}]","instr":"T. Johnson","start_date":"2024-09-25","end_date":"2024-12-06","srcdb":"202501"},{"key":"6040","code":"MTH 254H","title":"VECTOR CALCULUS I","crn":"11968","no":"002","total":"2","schd":"A","camp":"C","stat":"A","ssrFees":"10","isCancelled":"","meets":"MW 12-1:50p","mpkey":"2094","meetingTimes":"[{\"meet_day\":\"0\",\"start_time\":\"1200\",\"end_time\":\"1350\"},{\"meet_day\":\"2\",\"start_time\":\"1200\",\"end_time\":\"1350\"}]","instr":"C. Orum","start_date":"2024-09-25","end_date":"2024-12-06","srcdb":"202501"}]}