{"srcdb":"202501","count":1,"results":[{"key":"6097","code":"MTH 481","title":"APPLIED ORDINARY DIFFERENTIAL EQUATIONS","crn":"10147","no":"010","total":"1","schd":"A","camp":"C","stat":"A","ssrFees":"","isCancelled":"","meets":"MWF 11-11:50a","mpkey":"2065","meetingTimes":"[{\"meet_day\":\"0\",\"start_time\":\"1100\",\"end_time\":\"1150\"},{\"meet_day\":\"2\",\"start_time\":\"1100\",\"end_time\":\"1150\"},{\"meet_day\":\"4\",\"start_time\":\"1100\",\"end_time\":\"1150\"}]","instr":"M. Peszynska","start_date":"2024-09-25","end_date":"2024-12-06","srcdb":"202501"}]}