{"srcdb":"202501","count":3,"results":[{"key":"7254","code":"PH 507","title":"SEMINAR: SEM/ DEPARTMENTAL","crn":"10434","no":"111","total":"1","schd":"E","camp":"C","stat":"A","ssrFees":"","isCancelled":"","meets":"M 4-4:50p","mpkey":"2095","meetingTimes":"[{\"meet_day\":\"0\",\"start_time\":\"1600\",\"end_time\":\"1650\"}]","instr":"J. Hazboun","start_date":"2024-09-25","end_date":"2024-12-06","srcdb":"202501"},{"key":"7255","code":"PH 507","title":"SEMINAR: SEM/ SOLID STATE PHYSICS","crn":"10436","no":"131","total":"2","schd":"E","camp":"C","stat":"A","ssrFees":"","isCancelled":"","meets":"W 4-4:50p","mpkey":"2303","meetingTimes":"[{\"meet_day\":\"2\",\"start_time\":\"1600\",\"end_time\":\"1650\"}]","instr":"Y. Li","start_date":"2024-09-25","end_date":"2024-12-06","srcdb":"202501"},{"key":"7256","code":"PH 507","title":"SEMINAR: SEM/ SOLID STATE PHYSICS","crn":"10437","no":"132","total":"2","schd":"E","camp":"C","stat":"A","ssrFees":"","isCancelled":"","meets":"W 4-4:50p","mpkey":"2303","meetingTimes":"[{\"meet_day\":\"2\",\"start_time\":\"1600\",\"end_time\":\"1650\"}]","instr":"Y. Li","start_date":"2024-09-25","end_date":"2024-12-06","srcdb":"202501"}]}