{"srcdb":"202501","count":8,"results":[{"key":"7630","code":"PSY 298","title":"QUANTITATIVE METHODS IN PSYCHOLOGICAL SCIENCE","crn":"15097","no":"001","total":"8","schd":"A","camp":"C","stat":"A","ssrFees":"","isCancelled":"","meets":"MW 8:30-9:50a","mpkey":"2579","meetingTimes":"[{\"meet_day\":\"0\",\"start_time\":\"830\",\"end_time\":\"950\"},{\"meet_day\":\"2\",\"start_time\":\"830\",\"end_time\":\"950\"}]","instr":"J. Goldman","start_date":"2024-09-25","end_date":"2024-12-06","srcdb":"202501"},{"key":"7631","code":"PSY 298","title":"QUANTITATIVE METHODS IN PSYCHOLOGICAL SCIENCE","crn":"16356","no":"010","total":"8","schd":"D","camp":"C","stat":"F","ssrFees":"","isCancelled":"","meets":"M 10-11:50a","mpkey":"2082","meetingTimes":"[{\"meet_day\":\"0\",\"start_time\":\"1000\",\"end_time\":\"1150\"}]","instr":"S. Reed","start_date":"2024-09-25","end_date":"2024-12-06","srcdb":"202501"},{"key":"7632","code":"PSY 298","title":"QUANTITATIVE METHODS IN PSYCHOLOGICAL SCIENCE","crn":"16360","no":"011","total":"8","schd":"D","camp":"C","stat":"A","ssrFees":"","isCancelled":"","meets":"M 12-1:50p","mpkey":"2052","meetingTimes":"[{\"meet_day\":\"0\",\"start_time\":\"1200\",\"end_time\":\"1350\"}]","instr":"J. Canen","start_date":"2024-09-25","end_date":"2024-12-06","srcdb":"202501"},{"key":"7633","code":"PSY 298","title":"QUANTITATIVE METHODS IN PSYCHOLOGICAL SCIENCE","crn":"16367","no":"013","total":"8","schd":"D","camp":"C","stat":"A","ssrFees":"","isCancelled":"","meets":"W 10-11:50a","mpkey":"2084","meetingTimes":"[{\"meet_day\":\"2\",\"start_time\":\"1000\",\"end_time\":\"1150\"}]","instr":"S. Reed","start_date":"2024-09-25","end_date":"2024-12-06","srcdb":"202501"},{"key":"7635","code":"PSY 298","title":"QUANTITATIVE METHODS IN PSYCHOLOGICAL SCIENCE","crn":"19171","no":"014","total":"8","schd":"D","camp":"C","stat":"A","ssrFees":"","isCancelled":"","meets":"W 12-1:50p","mpkey":"2085","meetingTimes":"[{\"meet_day\":\"2\",\"start_time\":\"1200\",\"end_time\":\"1350\"}]","instr":"J. Canen","start_date":"2024-09-25","end_date":"2024-12-06","srcdb":"202501"},{"key":"7629","code":"PSY 298","title":"QUANTITATIVE METHODS IN PSYCHOLOGICAL SCIENCE","crn":"14326","no":"400","total":"8","schd":"Y","camp":"DI","stat":"A","ssrFees":"","isCancelled":"","meets":"","mpkey":"1","meetingTimes":"[]","instr":"C. Kidder","start_date":"2024-09-25","end_date":"2024-12-06","srcdb":"202501"},{"key":"7634","code":"PSY 298","title":"QUANTITATIVE METHODS IN PSYCHOLOGICAL SCIENCE","crn":"19117","no":"401","total":"8","schd":"Y","camp":"DI","stat":"A","ssrFees":"","isCancelled":"","meets":"","mpkey":"1","meetingTimes":"[]","instr":"W. Zimmerman","start_date":"2024-09-25","end_date":"2024-12-06","srcdb":"202501"},{"key":"7636","code":"PSY 298","title":"QUANTITATIVE METHODS IN PSYCHOLOGICAL SCIENCE","crn":"19568","no":"402","total":"8","schd":"Y","camp":"DI","stat":"A","ssrFees":"","isCancelled":"","meets":"","mpkey":"1","meetingTimes":"[]","instr":"K. Long","start_date":"2024-09-25","end_date":"2024-12-06","srcdb":"202501"}]}