{"srcdb":"202503","count":3,"results":[{"key":"2142","code":"CS 321","title":"INTRODUCTION TO THEORY OF COMPUTATION","crn":"54021","no":"400","total":"3","schd":"Y","camp":"DB","stat":"A","ssrFees":"","isCancelled":"","meets":"","mpkey":"1","meetingTimes":"[]","instr":"T. Alcon","start_date":"2025-03-31","end_date":"2025-06-06","srcdb":"202503"},{"key":"2143","code":"CS 321","title":"INTRODUCTION TO THEORY OF COMPUTATION","crn":"55353","no":"401","total":"3","schd":"Y","camp":"DB","stat":"A","ssrFees":"","isCancelled":"","meets":"","mpkey":"1","meetingTimes":"[]","instr":"Staff","start_date":"2025-03-31","end_date":"2025-06-06","srcdb":"202503"},{"key":"2144","code":"CS 321","title":"INTRODUCTION TO THEORY OF COMPUTATION","crn":"58176","no":"402","total":"3","schd":"Y","camp":"DB","stat":"A","ssrFees":"","isCancelled":"","meets":"","mpkey":"1","meetingTimes":"[]","instr":"Staff","start_date":"2025-03-31","end_date":"2025-06-06","srcdb":"202503"}]}