{"srcdb":"202503","count":2,"results":[{"key":"2467","code":"CS 559","title":"TOPICS IN GRAPHICS AND VISION: ST/VIRTUAL & AUGMENTED REALITY","crn":"58656","no":"010","total":"2","schd":"A","camp":"C","stat":"A","ssrFees":"","isCancelled":"","meets":"MF 1-1:50p","mpkey":"2385","meetingTimes":"[{\"meet_day\":\"0\",\"start_time\":\"1300\",\"end_time\":\"1350\"},{\"meet_day\":\"4\",\"start_time\":\"1300\",\"end_time\":\"1350\"}]","instr":"R. De Amicis","start_date":"2025-03-31","end_date":"2025-06-06","srcdb":"202503"},{"key":"2468","code":"CS 559","title":"TOPICS IN GRAPHICS AND VISION: ST/VIRTUAL & AUGMENTED REALITY","crn":"58657","no":"011","total":"2","schd":"D","camp":"C","stat":"A","ssrFees":"","isCancelled":"","meets":"W 12-1:50p","mpkey":"2085","meetingTimes":"[{\"meet_day\":\"2\",\"start_time\":\"1200\",\"end_time\":\"1350\"}]","instr":"R. De Amicis","start_date":"2025-03-31","end_date":"2025-06-06","srcdb":"202503"}]}