{"srcdb":"202503","count":23,"results":[{"key":"2821","code":"ECE 601","title":"RESEARCH","crn":"50316","no":"001","total":"23","schd":"G","camp":"C","stat":"A","ssrFees":"","isCancelled":"","meets":"","mpkey":"1","meetingTimes":"[]","instr":"Staff","start_date":"2025-03-31","end_date":"2025-06-06","srcdb":"202503"},{"key":"2822","code":"ECE 601","title":"RESEARCH","crn":"53132","no":"002","total":"23","schd":"G","camp":"C","stat":"A","ssrFees":"","isCancelled":"","meets":"","mpkey":"1","meetingTimes":"[]","instr":"Staff","start_date":"2025-03-31","end_date":"2025-06-06","srcdb":"202503"},{"key":"2823","code":"ECE 601","title":"RESEARCH","crn":"53133","no":"003","total":"23","schd":"G","camp":"C","stat":"A","ssrFees":"","isCancelled":"","meets":"","mpkey":"1","meetingTimes":"[]","instr":"Staff","start_date":"2025-03-31","end_date":"2025-06-06","srcdb":"202503"},{"key":"2824","code":"ECE 601","title":"RESEARCH","crn":"53134","no":"004","total":"23","schd":"G","camp":"C","stat":"A","ssrFees":"","isCancelled":"","meets":"","mpkey":"1","meetingTimes":"[]","instr":"Staff","start_date":"2025-03-31","end_date":"2025-06-06","srcdb":"202503"},{"key":"2825","code":"ECE 601","title":"RESEARCH","crn":"53135","no":"005","total":"23","schd":"G","camp":"C","stat":"A","ssrFees":"","isCancelled":"","meets":"","mpkey":"1","meetingTimes":"[]","instr":"Staff","start_date":"2025-03-31","end_date":"2025-06-06","srcdb":"202503"},{"key":"2826","code":"ECE 601","title":"RESEARCH","crn":"53136","no":"006","total":"23","schd":"G","camp":"C","stat":"A","ssrFees":"","isCancelled":"","meets":"","mpkey":"1","meetingTimes":"[]","instr":"Staff","start_date":"2025-03-31","end_date":"2025-06-06","srcdb":"202503"},{"key":"2827","code":"ECE 601","title":"RESEARCH","crn":"53137","no":"007","total":"23","schd":"G","camp":"C","stat":"A","ssrFees":"","isCancelled":"","meets":"","mpkey":"1","meetingTimes":"[]","instr":"Staff","start_date":"2025-03-31","end_date":"2025-06-06","srcdb":"202503"},{"key":"2828","code":"ECE 601","title":"RESEARCH","crn":"53138","no":"008","total":"23","schd":"G","camp":"C","stat":"A","ssrFees":"","isCancelled":"","meets":"","mpkey":"1","meetingTimes":"[]","instr":"Staff","start_date":"2025-03-31","end_date":"2025-06-06","srcdb":"202503"},{"key":"2829","code":"ECE 601","title":"RESEARCH","crn":"53139","no":"009","total":"23","schd":"G","camp":"C","stat":"A","ssrFees":"","isCancelled":"","meets":"","mpkey":"1","meetingTimes":"[]","instr":"Staff","start_date":"2025-03-31","end_date":"2025-06-06","srcdb":"202503"},{"key":"2830","code":"ECE 601","title":"RESEARCH","crn":"53140","no":"010","total":"23","schd":"G","camp":"C","stat":"A","ssrFees":"","isCancelled":"","meets":"","mpkey":"1","meetingTimes":"[]","instr":"Staff","start_date":"2025-03-31","end_date":"2025-06-06","srcdb":"202503"},{"key":"2831","code":"ECE 601","title":"RESEARCH","crn":"53141","no":"011","total":"23","schd":"G","camp":"C","stat":"A","ssrFees":"","isCancelled":"","meets":"","mpkey":"1","meetingTimes":"[]","instr":"Staff","start_date":"2025-03-31","end_date":"2025-06-06","srcdb":"202503"},{"key":"2832","code":"ECE 601","title":"RESEARCH","crn":"53142","no":"012","total":"23","schd":"G","camp":"C","stat":"A","ssrFees":"","isCancelled":"","meets":"","mpkey":"1","meetingTimes":"[]","instr":"Staff","start_date":"2025-03-31","end_date":"2025-06-06","srcdb":"202503"},{"key":"2833","code":"ECE 601","title":"RESEARCH","crn":"53143","no":"013","total":"23","schd":"G","camp":"C","stat":"A","ssrFees":"","isCancelled":"","meets":"","mpkey":"1","meetingTimes":"[]","instr":"Staff","start_date":"2025-03-31","end_date":"2025-06-06","srcdb":"202503"},{"key":"2834","code":"ECE 601","title":"RESEARCH","crn":"53144","no":"014","total":"23","schd":"G","camp":"C","stat":"A","ssrFees":"","isCancelled":"","meets":"","mpkey":"1","meetingTimes":"[]","instr":"Staff","start_date":"2025-03-31","end_date":"2025-06-06","srcdb":"202503"},{"key":"2835","code":"ECE 601","title":"RESEARCH","crn":"53145","no":"015","total":"23","schd":"G","camp":"C","stat":"A","ssrFees":"","isCancelled":"","meets":"","mpkey":"1","meetingTimes":"[]","instr":"Staff","start_date":"2025-03-31","end_date":"2025-06-06","srcdb":"202503"},{"key":"2837","code":"ECE 601","title":"RESEARCH","crn":"53838","no":"016","total":"23","schd":"G","camp":"C","stat":"A","ssrFees":"","isCancelled":"","meets":"","mpkey":"1","meetingTimes":"[]","instr":"Staff","start_date":"2025-03-31","end_date":"2025-06-06","srcdb":"202503"},{"key":"2838","code":"ECE 601","title":"RESEARCH","crn":"53875","no":"017","total":"23","schd":"G","camp":"C","stat":"A","ssrFees":"","isCancelled":"","meets":"","mpkey":"1","meetingTimes":"[]","instr":"Staff","start_date":"2025-03-31","end_date":"2025-06-06","srcdb":"202503"},{"key":"2836","code":"ECE 601","title":"RESEARCH","crn":"53146","no":"018","total":"23","schd":"G","camp":"C","stat":"A","ssrFees":"","isCancelled":"","meets":"","mpkey":"1","meetingTimes":"[]","instr":"Staff","start_date":"2025-03-31","end_date":"2025-06-06","srcdb":"202503"},{"key":"2839","code":"ECE 601","title":"RESEARCH","crn":"53876","no":"019","total":"23","schd":"G","camp":"C","stat":"A","ssrFees":"","isCancelled":"","meets":"","mpkey":"1","meetingTimes":"[]","instr":"Staff","start_date":"2025-03-31","end_date":"2025-06-06","srcdb":"202503"},{"key":"2840","code":"ECE 601","title":"RESEARCH","crn":"53891","no":"020","total":"23","schd":"G","camp":"C","stat":"A","ssrFees":"","isCancelled":"","meets":"","mpkey":"1","meetingTimes":"[]","instr":"Staff","start_date":"2025-03-31","end_date":"2025-06-06","srcdb":"202503"},{"key":"2841","code":"ECE 601","title":"RESEARCH","crn":"54731","no":"021","total":"23","schd":"G","camp":"C","stat":"A","ssrFees":"","isCancelled":"","meets":"","mpkey":"1","meetingTimes":"[]","instr":"Staff","start_date":"2025-03-31","end_date":"2025-06-06","srcdb":"202503"},{"key":"2842","code":"ECE 601","title":"RESEARCH","crn":"55533","no":"022","total":"23","schd":"G","camp":"C","stat":"A","ssrFees":"","isCancelled":"","meets":"","mpkey":"1","meetingTimes":"[]","instr":"Staff","start_date":"2025-03-31","end_date":"2025-06-06","srcdb":"202503"},{"key":"2843","code":"ECE 601","title":"RESEARCH","crn":"58260","no":"023","total":"23","schd":"G","camp":"C","stat":"A","ssrFees":"","isCancelled":"","meets":"","mpkey":"1","meetingTimes":"[]","instr":"Staff","start_date":"2025-03-31","end_date":"2025-06-06","srcdb":"202503"}]}