{"srcdb":"202503","count":2,"results":[{"key":"4463","code":"HST 407","title":"^SEMINAR","crn":"51466","no":"001","total":"2","schd":"E","camp":"C","stat":"A","ssrFees":"","isCancelled":"","meets":"MW 12-1:50p","mpkey":"2094","meetingTimes":"[{\"meet_day\":\"0\",\"start_time\":\"1200\",\"end_time\":\"1350\"},{\"meet_day\":\"2\",\"start_time\":\"1200\",\"end_time\":\"1350\"}]","instr":"J. Bawden","start_date":"2025-03-31","end_date":"2025-06-06","srcdb":"202503"},{"key":"4464","code":"HST 407","title":"^SEMINAR","crn":"53008","no":"400","total":"2","schd":"Y","camp":"DB","stat":"A","ssrFees":"","isCancelled":"","meets":"","mpkey":"1","meetingTimes":"[]","instr":"M. Lynch","start_date":"2025-03-31","end_date":"2025-06-06","srcdb":"202503"}]}