{"srcdb":"202503","count":4,"results":[{"key":"4946","code":"ME 412","title":"DESIGN OF MECHANISMS","crn":"53980","no":"001","total":"4","schd":"A","camp":"C","stat":"A","ssrFees":"","isCancelled":"","meets":"TR 2-3:20p","mpkey":"2068","meetingTimes":"[{\"meet_day\":\"1\",\"start_time\":\"1400\",\"end_time\":\"1520\"},{\"meet_day\":\"3\",\"start_time\":\"1400\",\"end_time\":\"1520\"}]","instr":"M. Campbell","start_date":"2025-03-31","end_date":"2025-06-06","srcdb":"202503"},{"key":"4947","code":"ME 412","title":"DESIGN OF MECHANISMS","crn":"53981","no":"010","total":"4","schd":"D","camp":"C","stat":"A","ssrFees":"","isCancelled":"","meets":"F 10-11:50a","mpkey":"2247","meetingTimes":"[{\"meet_day\":\"4\",\"start_time\":\"1000\",\"end_time\":\"1150\"}]","instr":"M. Campbell","start_date":"2025-03-31","end_date":"2025-06-06","srcdb":"202503"},{"key":"4948","code":"ME 412","title":"DESIGN OF MECHANISMS","crn":"54091","no":"011","total":"4","schd":"D","camp":"C","stat":"A","ssrFees":"","isCancelled":"","meets":"F 12-1:50p","mpkey":"2250","meetingTimes":"[{\"meet_day\":\"4\",\"start_time\":\"1200\",\"end_time\":\"1350\"}]","instr":"M. Campbell","start_date":"2025-03-31","end_date":"2025-06-06","srcdb":"202503"},{"key":"4949","code":"ME 412","title":"DESIGN OF MECHANISMS","crn":"54092","no":"012","total":"4","schd":"D","camp":"C","stat":"A","ssrFees":"","isCancelled":"","meets":"F 2-3:50p","mpkey":"2437","meetingTimes":"[{\"meet_day\":\"4\",\"start_time\":\"1400\",\"end_time\":\"1550\"}]","instr":"M. Campbell","start_date":"2025-03-31","end_date":"2025-06-06","srcdb":"202503"}]}