{"srcdb":"202503","count":3,"results":[{"key":"7505","code":"WLC 337","title":"*JAPANESE CULTURE III","crn":"53334","no":"001","total":"3","schd":"A","camp":"C","stat":"A","ssrFees":"","isCancelled":"","meets":"TR 12-1:20p","mpkey":"2062","meetingTimes":"[{\"meet_day\":\"1\",\"start_time\":\"1200\",\"end_time\":\"1320\"},{\"meet_day\":\"3\",\"start_time\":\"1200\",\"end_time\":\"1320\"}]","instr":"M. Diem","start_date":"2025-03-31","end_date":"2025-06-06","srcdb":"202503"},{"key":"7504","code":"WLC 337","title":"*JAPANESE CULTURE III","crn":"53265","no":"400","total":"3","schd":"Y","camp":"DB","stat":"A","ssrFees":"","isCancelled":"","meets":"","mpkey":"1","meetingTimes":"[]","instr":"M. Diem","start_date":"2025-03-31","end_date":"2025-06-06","srcdb":"202503"},{"key":"7506","code":"WLC 337","title":"*JAPANESE CULTURE III","crn":"57309","no":"401","total":"3","schd":"Y","camp":"DB","stat":"A","ssrFees":"","isCancelled":"","meets":"","mpkey":"1","meetingTimes":"[]","instr":"N. Wingard","start_date":"2025-03-31","end_date":"2025-06-06","srcdb":"202503"}]}