{"srcdb":"202502","count":3,"results":[{"key":"753","code":"BA 410","title":"BUSINESS INTERNSHIP","crn":"30535","no":"001","total":"3","schd":"J","camp":"C","stat":"A","ssrFees":"","isCancelled":"","meets":"","mpkey":"1","meetingTimes":"[]","instr":"J. Villalobos","start_date":"2025-01-06","end_date":"2025-03-14","srcdb":"202502"},{"key":"755","code":"BA 410","title":"BUSINESS INTERNSHIP","crn":"33746","no":"400","total":"3","schd":"Y","camp":"DB","stat":"A","ssrFees":"","isCancelled":"","meets":"","mpkey":"1","meetingTimes":"[]","instr":"J. Villalobos","start_date":"2025-01-06","end_date":"2025-03-14","srcdb":"202502"},{"key":"754","code":"BA 410","title":"BUSINESS INTERNSHIP","crn":"33082","no":"501","total":"3","schd":"J","camp":"B","stat":"A","ssrFees":"","isCancelled":"","meets":"","mpkey":"1","meetingTimes":"[]","instr":"K. Vierra","start_date":"2025-01-06","end_date":"2025-03-14","srcdb":"202502"}]}