{"srcdb":"202502","count":3,"results":[{"key":"1070","code":"BI 204","title":"*INTRODUCTORY BIOLOGY I","crn":"33318","no":"400","total":"3","schd":"Y","camp":"DI","stat":"A","ssrFees":"","isCancelled":"","meets":"","mpkey":"1","meetingTimes":"[]","instr":"J. Rose","start_date":"2025-01-06","end_date":"2025-03-14","srcdb":"202502"},{"key":"1071","code":"BI 204","title":"*INTRODUCTORY BIOLOGY I","crn":"34315","no":"401","total":"3","schd":"Y","camp":"DI","stat":"A","ssrFees":"","isCancelled":"","meets":"","mpkey":"1","meetingTimes":"[]","instr":"S. Wasala","start_date":"2025-01-06","end_date":"2025-03-14","srcdb":"202502"},{"key":"1072","code":"BI 204","title":"*INTRODUCTORY BIOLOGY I","crn":"34656","no":"402","total":"3","schd":"Y","camp":"DI","stat":"A","ssrFees":"","isCancelled":"","meets":"","mpkey":"1","meetingTimes":"[]","instr":"J. Smyth","start_date":"2025-01-06","end_date":"2025-03-14","srcdb":"202502"}]}