{"srcdb":"202502","count":3,"results":[{"key":"4363","code":"HDFS 310","title":"HUMAN SERVICES PRACTICUM","crn":"34034","no":"001","total":"3","schd":"M","camp":"C","stat":"A","ssrFees":"","isCancelled":"","meets":"R 12-1:50p","mpkey":"2040","meetingTimes":"[{\"meet_day\":\"3\",\"start_time\":\"1200\",\"end_time\":\"1350\"}]","instr":"T. Randall","start_date":"2025-01-06","end_date":"2025-03-14","srcdb":"202502"},{"key":"4365","code":"HDFS 310","title":"HUMAN SERVICES PRACTICUM","crn":"34438","no":"400","total":"3","schd":"Y","camp":"DB","stat":"A","ssrFees":"","isCancelled":"","meets":"","mpkey":"1","meetingTimes":"[]","instr":"T. Randall","start_date":"2025-01-06","end_date":"2025-03-14","srcdb":"202502"},{"key":"4364","code":"HDFS 310","title":"HUMAN SERVICES PRACTICUM","crn":"34095","no":"501","total":"3","schd":"M","camp":"B","stat":"A","ssrFees":"","isCancelled":"","meets":"T 2-3:50p","mpkey":"2104","meetingTimes":"[{\"meet_day\":\"1\",\"start_time\":\"1400\",\"end_time\":\"1550\"}]","instr":"D. Lynn","start_date":"2025-01-06","end_date":"2025-03-14","srcdb":"202502"}]}