{"srcdb":"202502","count":6,"results":[{"key":"5661","code":"MTH 607","title":"SEMINAR: SEM/ ALGEBRA & NUMBER THEORY","crn":"31216","no":"009","total":"1","schd":"E","camp":"C","stat":"A","ssrFees":"","isCancelled":"","meets":"T 11-11:50a","mpkey":"2395","meetingTimes":"[{\"meet_day\":\"1\",\"start_time\":\"1100\",\"end_time\":\"1150\"}]","instr":"T. Schmidt","start_date":"2025-01-06","end_date":"2025-03-14","srcdb":"202502"},{"key":"5659","code":"MTH 607","title":"SEMINAR: SEM/ ANALYSIS","crn":"31214","no":"007","total":"1","schd":"E","camp":"C","stat":"A","ssrFees":"","isCancelled":"","meets":"M 12-12:50p","mpkey":"2370","meetingTimes":"[{\"meet_day\":\"0\",\"start_time\":\"1200\",\"end_time\":\"1250\"}]","instr":"R. Dascaliuc","start_date":"2025-01-06","end_date":"2025-03-14","srcdb":"202502"},{"key":"5658","code":"MTH 607","title":"SEMINAR: SEM/ APPL MATH COMP","crn":"31213","no":"006","total":"1","schd":"E","camp":"C","stat":"A","ssrFees":"","isCancelled":"","meets":"F 12-12:50p","mpkey":"2237","meetingTimes":"[{\"meet_day\":\"4\",\"start_time\":\"1200\",\"end_time\":\"1250\"}]","instr":"Staff","start_date":"2025-01-06","end_date":"2025-03-14","srcdb":"202502"},{"key":"5660","code":"MTH 607","title":"SEMINAR: SEM/ GEOMETRY/TOPOLOGY","crn":"31215","no":"008","total":"1","schd":"E","camp":"C","stat":"A","ssrFees":"","isCancelled":"","meets":"M 12-12:50p","mpkey":"2370","meetingTimes":"[{\"meet_day\":\"0\",\"start_time\":\"1200\",\"end_time\":\"1250\"}]","instr":"Staff","start_date":"2025-01-06","end_date":"2025-03-14","srcdb":"202502"},{"key":"5662","code":"MTH 607","title":"SEMINAR: SEM/ MATHEMATICAL BIOLOGY","crn":"36321","no":"001","total":"1","schd":"E","camp":"C","stat":"A","ssrFees":"","isCancelled":"","meets":"F 10-10:50a","mpkey":"2022","meetingTimes":"[{\"meet_day\":\"4\",\"start_time\":\"1000\",\"end_time\":\"1050\"}]","instr":"Staff","start_date":"2025-01-06","end_date":"2025-03-14","srcdb":"202502"},{"key":"5663","code":"MTH 607","title":"SEMINAR: SEM/ PROBABILITY & DATA SCIEN","crn":"38383","no":"003","total":"1","schd":"E","camp":"C","stat":"A","ssrFees":"","isCancelled":"","meets":"T 3-3:50p","mpkey":"2059","meetingTimes":"[{\"meet_day\":\"1\",\"start_time\":\"1500\",\"end_time\":\"1550\"}]","instr":"Staff","start_date":"2025-01-06","end_date":"2025-03-14","srcdb":"202502"}]}