{"srcdb":"202502","count":1,"results":[{"key":"6196","code":"OC 671","title":"GEOPHYSICAL FLUID DYNAMICS I","crn":"31457","no":"001","total":"1","schd":"A","camp":"C","stat":"A","ssrFees":"","isCancelled":"","meets":"MWRF 8-8:50a","mpkey":"7855","meetingTimes":"[{\"meet_day\":\"0\",\"start_time\":\"800\",\"end_time\":\"850\"},{\"meet_day\":\"2\",\"start_time\":\"800\",\"end_time\":\"850\"},{\"meet_day\":\"3\",\"start_time\":\"800\",\"end_time\":\"850\"},{\"meet_day\":\"4\",\"start_time\":\"800\",\"end_time\":\"850\"}]","instr":"R. Matano","start_date":"2025-01-06","end_date":"2025-03-14","srcdb":"202502"}]}