{"srcdb":"202502","count":3,"results":[{"key":"6339","code":"PAC 139","title":"HIP HOP DANCE","crn":"33812","no":"001","total":"3","schd":"H","camp":"C","stat":"A","ssrFees":"49","isCancelled":"","meets":"MW 5-5:50p","mpkey":"2119","meetingTimes":"[{\"meet_day\":\"0\",\"start_time\":\"1700\",\"end_time\":\"1750\"},{\"meet_day\":\"2\",\"start_time\":\"1700\",\"end_time\":\"1750\"}]","instr":"L. Hepner","start_date":"2025-01-06","end_date":"2025-03-14","srcdb":"202502"},{"key":"6340","code":"PAC 139","title":"HIP HOP DANCE","crn":"35278","no":"002","total":"3","schd":"H","camp":"C","stat":"A","ssrFees":"49","isCancelled":"","meets":"MW 4-4:50p","mpkey":"2088","meetingTimes":"[{\"meet_day\":\"0\",\"start_time\":\"1600\",\"end_time\":\"1650\"},{\"meet_day\":\"2\",\"start_time\":\"1600\",\"end_time\":\"1650\"}]","instr":"L. Hepner","start_date":"2025-01-06","end_date":"2025-03-14","srcdb":"202502"},{"key":"6338","code":"PAC 139","title":"HIP HOP DANCE","crn":"33811","no":"003","total":"3","schd":"H","camp":"C","stat":"A","ssrFees":"49","isCancelled":"","meets":"TR 1-1:50p","mpkey":"2224","meetingTimes":"[{\"meet_day\":\"1\",\"start_time\":\"1300\",\"end_time\":\"1350\"},{\"meet_day\":\"3\",\"start_time\":\"1300\",\"end_time\":\"1350\"}]","instr":"G. Gangelhoff","start_date":"2025-01-06","end_date":"2025-03-14","srcdb":"202502"}]}