{"srcdb":"202502","count":2,"results":[{"key":"7484","code":"SPAN 337","title":"TEXTOS Y NARRATIVAS DEL MUNDO HISPANOHABLANTE: TEXTS AND NARRATIVES OF THE SPANISH-SPEAKING WORLD","crn":"34575","no":"001","total":"2","schd":"A","camp":"C","stat":"A","ssrFees":"","isCancelled":"","meets":"TR 10-11:20a","mpkey":"2179","meetingTimes":"[{\"meet_day\":\"1\",\"start_time\":\"1000\",\"end_time\":\"1120\"},{\"meet_day\":\"3\",\"start_time\":\"1000\",\"end_time\":\"1120\"}]","instr":"A. Warren","start_date":"2025-01-06","end_date":"2025-03-14","srcdb":"202502"},{"key":"7483","code":"SPAN 337","title":"TEXTOS Y NARRATIVAS DEL MUNDO HISPANOHABLANTE: TEXTS AND NARRATIVES OF THE SPANISH-SPEAKING WORLD","crn":"33285","no":"400","total":"2","schd":"Y","camp":"DB","stat":"A","ssrFees":"","isCancelled":"","meets":"","mpkey":"1","meetingTimes":"[]","instr":"L. Mulas","start_date":"2025-01-06","end_date":"2025-03-14","srcdb":"202502"}]}