{"srcdb":"202502","count":2,"results":[{"key":"7575","code":"ST 515","title":"DESIGN AND ANALYSIS OF PLANNED EXPERIMENTS","crn":"35993","no":"400","total":"2","schd":"Y","camp":"DB","stat":"A","ssrFees":"","isCancelled":"","meets":"","mpkey":"1","meetingTimes":"[]","instr":"K. Rott","start_date":"2025-01-06","end_date":"2025-03-14","srcdb":"202502"},{"key":"7576","code":"ST 515","title":"DESIGN AND ANALYSIS OF PLANNED EXPERIMENTS","crn":"35994","no":"401","total":"2","schd":"Y","camp":"DB","stat":"A","ssrFees":"","isCancelled":"","meets":"","mpkey":"1","meetingTimes":"[]","instr":"K. Rott","start_date":"2025-01-06","end_date":"2025-03-14","srcdb":"202502"}]}